{"key": "/books/OL3170408M", "title": "Forbidden books in American public libraries, 1876-1939", "subtitle": "a study in cultural change", "publishers": ["Greenwood Press"], "authors": ["Evelyn Geller"], "isbn_10": "0313238081", "isbn_13": null, "publish_date": "1984", "subjects": ["Public libraries -- Censorship -- United States -- History.", "Censorship -- United States -- History.", "Library science -- United States -- History.", "Books and reading -- United States -- History.", "Freedom of information -- United States -- History."]}