{"key": "/books/OL5708675M", "title": "Length of service of Pennsylvania high school teachers", "subtitle": "the relationship between length of teaching service and certain economic, social, and educational factors, with a consideration of future needs and the supply.", "publishers": ["AMS Press"], "authors": ["Lyman Henry Van Houten"], "isbn_10": "0404555225", "isbn_13": null, "publish_date": "1972", "subjects": ["High school teachers -- Tenure -- Pennsylvania.", "High school teachers -- Supply and demand -- Pennsylvania."]}