{"key": "/books/OL7661092M", "title": "The Last Manchu", "subtitle": "The Autobiography of Henry Pu Yi, Last Emperor of China", "publishers": ["Pocket"], "authors": ["Pu Yi"], "isbn_10": "0671651889", "isbn_13": "9780671651886", "publish_date": "December 1, 1987", "subjects": ["Movie-TV Tie-In - General", "Historical - General", "China - History - 20th Century", "Biography / Autobiography", "P'u-i,", "Biography/Autobiography", "P'u-i", "Kings and rulers", "Fiction / Movie or Television Tie-In", "1906-1967", "Biography", "China"]}