{"key": "/books/OL7830821M", "title": "Twentieth Century Classics (Architecture 3s) Walter Gropius, Le Corbusier, Louis I. Kahn", "subtitle": null, "publishers": ["Phaidon Press"], "authors": ["Dennis Sharp"], "isbn_10": "0714838683", "isbn_13": "9780714838687", "publish_date": "July 29, 1999", "subjects": ["Design styles: from c 1900 -", "Individual architects", "Public buildings: civic, commercial, industrial, etc", "Criticism", "20th Century Architecture", "Architecture", "History - Specific Styles", "20th century", "Architecture / Public, Commercial, or Industrial Buildings", "Architecture, Modern"]}